nanomelt/__init__.py
nanomelt/__main__.py
nanomelt/predict.py
nanomelt/train.py
nanomelt/model/__init__.py
nanomelt/model/ens_averaging.py
nanomelt/model/final_retrain.py
nanomelt/model/indiv_reg_train.py
nanomelt/model/nanomelt.py
nanomelt/model/stacking.py
nanomelt/model/embedding/OLDfasta_embed.py
nanomelt/model/embedding/__init__.py
nanomelt/model/embedding/fasta_embed.py
nanomelt/model/modules/__init__.py
nanomelt/model/modules/clustering.py
nanomelt/model/modules/ensemble.py
nanomelt/model/modules/regs.py
nanomelt/model/modules/strat_nest.py
nanomelt/model/modules/utils.py
nanomelt/model/modules/alignment/__init__.py
nanomelt/model/modules/alignment/aho_consensus.py
nanomelt/model/modules/alignment/blossum.py
nanomelt/model/modules/alignment/csv_dict.py
nanomelt/model/modules/alignment/liabilities.py
nanomelt/model/modules/alignment/misc.py
nanomelt/model/modules/alignment/mybio.py
nanomelt/model/modules/alignment/myparallel.py
nanomelt/model/modules/alignment/parse_pdb.py
nanomelt/model/modules/alignment/plotter.py
nanomelt/model/modules/alignment/structs.py
nanomelt/model/saved_models/__init__.py
nanomelt/model/saved_models/NanoMelt_finalmodel/GPR_onehot.joblib
nanomelt/model/saved_models/NanoMelt_finalmodel/GPR_vhse.joblib
nanomelt/model/saved_models/NanoMelt_finalmodel/SVR_esm1b.joblib
nanomelt/model/saved_models/NanoMelt_finalmodel/SVR_esm2_t30.joblib
nanomelt/model/saved_models/NanoMelt_finalmodel/__init__.py
nanomelt/model/saved_models/NanoMelt_finalmodel/ensemb_pred.csv
nanomelt/model/saved_models/NanoMelt_finalmodel/ridge_ensemb.joblib
nanomelt/model/saved_models/NanoMelt_finalmodel/submodels_pred.csv
nanomelt-1.2.0.dist-info/licenses/LICENSE
nanomelt-1.2.0.dist-info/METADATA
nanomelt-1.2.0.dist-info/WHEEL
nanomelt-1.2.0.dist-info/entry_points.txt
nanomelt-1.2.0.dist-info/top_level.txt
nanomelt-1.2.0.dist-info/RECORD
