Metadata-Version: 2.4
Name: nanomelt
Version: 1.2.0
Summary: A nanobody thermostability prediction tool
Author: Aubin Ramon
Author-email: ar2033@cam.ac.uk
License: CC BY-NC-SA 4.0
License-File: LICENSE
Requires-Dist: scikit-learn
Requires-Dist: scikit-learn-extra
Requires-Dist: joblib
Requires-Dist: fair-esm
Requires-Dist: ablang
Requires-Dist: Immunebuilder
Requires-Dist: transformers
Requires-Dist: antiberty
Requires-Dist: xgboost
Requires-Dist: lightgbm
Requires-Dist: kneed
Requires-Dist: matplotlib
Dynamic: author
Dynamic: author-email
Dynamic: description
Dynamic: license
Dynamic: license-file
Dynamic: requires-dist
Dynamic: summary
